buildout.cfg
changes.txt
setup.py
src/ore/__init__.py
src/ore.svn.egg-info/PKG-INFO
src/ore.svn.egg-info/SOURCES.txt
src/ore.svn.egg-info/dependency_links.txt
src/ore.svn.egg-info/namespace_packages.txt
src/ore.svn.egg-info/requires.txt
src/ore.svn.egg-info/top_level.txt
src/ore.svn.egg-info/zip-safe
src/ore/svn/__init__.py
src/ore/svn/_wire.py
src/ore/svn/context.py
src/ore/svn/directory.py
src/ore/svn/examples.txt
src/ore/svn/file.py
src/ore/svn/interfaces.py
src/ore/svn/log.py
src/ore/svn/manager.py
src/ore/svn/node.py
src/ore/svn/property.py
src/ore/svn/readme.txt
src/ore/svn/repos.py
src/ore/svn/resource.py
src/ore/svn/stream.py
src/ore/svn/todo.txt
src/ore/svn/tree.py
src/ore/svn/utils.py
src/ore/svn/tests/__init__.py
src/ore/svn/tests/_base.py
src/ore/svn/tests/all.py
src/ore/svn/tests/mkTestEnv.sh
src/ore/svn/tests/test_Directory.py
src/ore/svn/tests/test_File.py
src/ore/svn/tests/test_Node.py
src/ore/svn/tests/test_Properties.py
src/ore/svn/tests/test_Readme.py
src/ore/svn/tests/test_Transaction.py
src/ore/svn/tests/testrepo.dump.bz2
