Metadata-Version: 1.0
Name: ore.svn
Version: 1.0.5
Summary: An object oriented api for subversion with support for r/w
Home-page: https://svn.objectrealms.net/svn/public/ore.svn
Author: Kapil Thangavelu
Author-email: kapil.foss@objectrealms.net
License: http://www.apache.org/licenses/LICENSE-2.0
Keywords: zope svn subversion
Platform: UNKNOWN
Classifier: Development Status :: 5 - Production/Stable
Classifier: Intended Audience :: Developers
Classifier: Programming Language :: Python
Classifier: Topic :: Software Development :: Version Control
Classifier: Topic :: Software Development :: Libraries :: Python Modules
Classifier: Operating System :: Microsoft :: Windows
Classifier: Operating System :: Unix
